{
  "per_attr": {
    "clouds": {
      "candidate_universe": [
        {
          "index": 0,
          "source_group": "sefa",
          "source_rank": 0,
          "rho": 0.19827763363718987,
          "probe_gain": 0.0010554329783190042,
          "probe_sign": 1.0,
          "selection_rho": 0.19827763363718987
        },
        {
          "index": 1,
          "source_group": "sefa",
          "source_rank": 1,
          "rho": 0.1759875062853098,
          "probe_gain": 0.002892591553973034,
          "probe_sign": 1.0,
          "selection_rho": 0.1759875062853098
        },
        {
          "index": 2,
          "source_group": "sefa",
          "source_rank": 2,
          "rho": 0.21228170581161976,
          "probe_gain": 0.0018237010517623276,
          "probe_sign": 1.0,
          "selection_rho": 0.21228170581161976
        },
        {
          "index": 3,
          "source_group": "sefa",
          "source_rank": 3,
          "rho": 0.15591593366116285,
          "probe_gain": 0.0035288534418214113,
          "probe_sign": -1.0,
          "selection_rho": 0.15591593366116285
        },
        {
          "index": 4,
          "source_group": "sefa",
          "source_rank": 4,
          "rho": 0.20820385217666626,
          "probe_gain": 0.0005104067531647161,
          "probe_sign": -1.0,
          "selection_rho": 0.20820385217666626
        },
        {
          "index": 5,
          "source_group": "sefa",
          "source_rank": 5,
          "rho": 0.18020420148968697,
          "probe_gain": 0.00415652513038367,
          "probe_sign": -1.0,
          "selection_rho": 0.18020420148968697
        }
      ],
      "selected_candidate_offsets": {
        "risk_aware": [
          5,
          3,
          1,
          2
        ],
        "gain_only": [
          5,
          3,
          1,
          2
        ],
        "low_risk": [
          3,
          1,
          5,
          0
        ],
        "random": [
          1,
          3,
          4,
          5
        ],
        "high_risk": [
          2,
          4,
          0,
          5
        ]
      },
      "target_abs_delta_attr": 0.005795128410682082,
      "rows": {
        "risk_aware": [
          {
            "candidate_index": 5,
            "source_group": "sefa",
            "source_rank": 5,
            "rho": 0.18020420148968697,
            "selection_rho": 0.18020420148968697,
            "probe_gain": 0.00415652513038367,
            "probe_sign": -1.0,
            "alpha": 1.9212790644141489,
            "target_abs_delta_attr": 0.005795128410682082,
            "target_reached_on_calib": true,
            "calib_max_abs_delta_attr": 0.02206372789805755,
            "mean_delta_attr": 0.007955797394970432,
            "mean_abs_delta_attr": 0.01000642983126454,
            "mean_id_cos": 0.9594172975048423,
            "mean_lpips_proxy": 0.022559823148185387,
            "mean_lpips_true": 0.09313260635826737
          },
          {
            "candidate_index": 3,
            "source_group": "sefa",
            "source_rank": 3,
            "rho": 0.15591593366116285,
            "selection_rho": 0.15591593366116285,
            "probe_gain": 0.0035288534418214113,
            "probe_sign": -1.0,
            "alpha": 2.2005128058600687,
            "target_abs_delta_attr": 0.005795128410682082,
            "target_reached_on_calib": true,
            "calib_max_abs_delta_attr": 0.018321878276765347,
            "mean_delta_attr": 0.004314312205679016,
            "mean_abs_delta_attr": 0.009184921324049355,
            "mean_id_cos": 0.9341881861910224,
            "mean_lpips_proxy": 0.04608789988560602,
            "mean_lpips_true": 0.15847351064439863
          },
          {
            "candidate_index": 1,
            "source_group": "sefa",
            "source_rank": 1,
            "rho": 0.1759875062853098,
            "selection_rho": 0.1759875062853098,
            "probe_gain": 0.002892591553973034,
            "probe_sign": 1.0,
            "alpha": -4.828940209870235,
            "target_abs_delta_attr": 0.005795128410682082,
            "target_reached_on_calib": true,
            "calib_max_abs_delta_attr": 0.008183931233361363,
            "mean_delta_attr": -0.005357491070753895,
            "mean_abs_delta_attr": 0.011578495570574887,
            "mean_id_cos": 0.9072989141568542,
            "mean_lpips_proxy": 0.060159807617310435,
            "mean_lpips_true": 0.21027961722575128
          },
          {
            "candidate_index": 2,
            "source_group": "sefa",
            "source_rank": 2,
            "rho": 0.21228170581161976,
            "selection_rho": 0.21228170581161976,
            "probe_gain": 0.0018237010517623276,
            "probe_sign": 1.0,
            "alpha": -5.785369080195326,
            "target_abs_delta_attr": 0.005795128410682082,
            "target_reached_on_calib": true,
            "calib_max_abs_delta_attr": 0.006395893462467939,
            "mean_delta_attr": 0.0013430054968921468,
            "mean_abs_delta_attr": 0.015402238510432653,
            "mean_id_cos": 0.8476290190592408,
            "mean_lpips_proxy": 0.13359730719821528,
            "mean_lpips_true": 0.344283496029675
          }
        ],
        "gain_only": [
          {
            "candidate_index": 5,
            "source_group": "sefa",
            "source_rank": 5,
            "rho": 0.18020420148968697,
            "selection_rho": 0.18020420148968697,
            "probe_gain": 0.00415652513038367,
            "probe_sign": -1.0,
            "alpha": 1.9212790644141489,
            "target_abs_delta_attr": 0.005795128410682082,
            "target_reached_on_calib": true,
            "calib_max_abs_delta_attr": 0.02206372789805755,
            "mean_delta_attr": 0.007955797394970432,
            "mean_abs_delta_attr": 0.01000642983126454,
            "mean_id_cos": 0.9594172975048423,
            "mean_lpips_proxy": 0.022559823148185387,
            "mean_lpips_true": 0.09313260635826737
          },
          {
            "candidate_index": 3,
            "source_group": "sefa",
            "source_rank": 3,
            "rho": 0.15591593366116285,
            "selection_rho": 0.15591593366116285,
            "probe_gain": 0.0035288534418214113,
            "probe_sign": -1.0,
            "alpha": 2.2005128058600687,
            "target_abs_delta_attr": 0.005795128410682082,
            "target_reached_on_calib": true,
            "calib_max_abs_delta_attr": 0.018321878276765347,
            "mean_delta_attr": 0.004314312205679016,
            "mean_abs_delta_attr": 0.009184921324049355,
            "mean_id_cos": 0.9341881861910224,
            "mean_lpips_proxy": 0.04608789988560602,
            "mean_lpips_true": 0.15847351064439863
          },
          {
            "candidate_index": 1,
            "source_group": "sefa",
            "source_rank": 1,
            "rho": 0.1759875062853098,
            "selection_rho": 0.1759875062853098,
            "probe_gain": 0.002892591553973034,
            "probe_sign": 1.0,
            "alpha": -4.828940209870235,
            "target_abs_delta_attr": 0.005795128410682082,
            "target_reached_on_calib": true,
            "calib_max_abs_delta_attr": 0.008183931233361363,
            "mean_delta_attr": -0.005357491070753895,
            "mean_abs_delta_attr": 0.011578495570574887,
            "mean_id_cos": 0.9072989141568542,
            "mean_lpips_proxy": 0.060159807617310435,
            "mean_lpips_true": 0.21027961722575128
          },
          {
            "candidate_index": 2,
            "source_group": "sefa",
            "source_rank": 2,
            "rho": 0.21228170581161976,
            "selection_rho": 0.21228170581161976,
            "probe_gain": 0.0018237010517623276,
            "probe_sign": 1.0,
            "alpha": -5.785369080195326,
            "target_abs_delta_attr": 0.005795128410682082,
            "target_reached_on_calib": true,
            "calib_max_abs_delta_attr": 0.006395893462467939,
            "mean_delta_attr": 0.0013430054968921468,
            "mean_abs_delta_attr": 0.015402238510432653,
            "mean_id_cos": 0.8476290190592408,
            "mean_lpips_proxy": 0.13359730719821528,
            "mean_lpips_true": 0.344283496029675
          }
        ],
        "low_risk": [
          {
            "candidate_index": 3,
            "source_group": "sefa",
            "source_rank": 3,
            "rho": 0.15591593366116285,
            "selection_rho": 0.15591593366116285,
            "probe_gain": 0.0035288534418214113,
            "probe_sign": -1.0,
            "alpha": 2.2005128058600687,
            "target_abs_delta_attr": 0.005795128410682082,
            "target_reached_on_calib": true,
            "calib_max_abs_delta_attr": 0.018321878276765347,
            "mean_delta_attr": 0.004314312205679016,
            "mean_abs_delta_attr": 0.009184921324049355,
            "mean_id_cos": 0.9341881861910224,
            "mean_lpips_proxy": 0.04608789988560602,
            "mean_lpips_true": 0.15847351064439863
          },
          {
            "candidate_index": 1,
            "source_group": "sefa",
            "source_rank": 1,
            "rho": 0.1759875062853098,
            "selection_rho": 0.1759875062853098,
            "probe_gain": 0.002892591553973034,
            "probe_sign": 1.0,
            "alpha": -4.828940209870235,
            "target_abs_delta_attr": 0.005795128410682082,
            "target_reached_on_calib": true,
            "calib_max_abs_delta_attr": 0.008183931233361363,
            "mean_delta_attr": -0.005357491070753895,
            "mean_abs_delta_attr": 0.011578495570574887,
            "mean_id_cos": 0.9072989141568542,
            "mean_lpips_proxy": 0.060159807617310435,
            "mean_lpips_true": 0.21027961722575128
          },
          {
            "candidate_index": 5,
            "source_group": "sefa",
            "source_rank": 5,
            "rho": 0.18020420148968697,
            "selection_rho": 0.18020420148968697,
            "probe_gain": 0.00415652513038367,
            "probe_sign": -1.0,
            "alpha": 1.9212790644141489,
            "target_abs_delta_attr": 0.005795128410682082,
            "target_reached_on_calib": true,
            "calib_max_abs_delta_attr": 0.02206372789805755,
            "mean_delta_attr": 0.007955797394970432,
            "mean_abs_delta_attr": 0.01000642983126454,
            "mean_id_cos": 0.9594172975048423,
            "mean_lpips_proxy": 0.022559823148185387,
            "mean_lpips_true": 0.09313260635826737
          },
          {
            "candidate_index": 0,
            "source_group": "sefa",
            "source_rank": 0,
            "rho": 0.19827763363718987,
            "selection_rho": 0.19827763363718987,
            "probe_gain": 0.0010554329783190042,
            "probe_sign": 1.0,
            "alpha": -6.0,
            "target_abs_delta_attr": 0.005795128410682082,
            "target_reached_on_calib": false,
            "calib_max_abs_delta_attr": 0.004002573259640485,
            "mean_delta_attr": 0.0002476425579516217,
            "mean_abs_delta_attr": 0.010961703010252677,
            "mean_id_cos": 0.9230021014809608,
            "mean_lpips_proxy": 0.054003476863726974,
            "mean_lpips_true": 0.17663446080405265
          }
        ],
        "random": [
          {
            "candidate_index": 1,
            "source_group": "sefa",
            "source_rank": 1,
            "rho": 0.1759875062853098,
            "selection_rho": 0.1759875062853098,
            "probe_gain": 0.002892591553973034,
            "probe_sign": 1.0,
            "alpha": -4.828940209870235,
            "target_abs_delta_attr": 0.005795128410682082,
            "target_reached_on_calib": true,
            "calib_max_abs_delta_attr": 0.008183931233361363,
            "mean_delta_attr": -0.005357491070753895,
            "mean_abs_delta_attr": 0.011578495570574887,
            "mean_id_cos": 0.9072989141568542,
            "mean_lpips_proxy": 0.060159807617310435,
            "mean_lpips_true": 0.21027961722575128
          },
          {
            "candidate_index": 3,
            "source_group": "sefa",
            "source_rank": 3,
            "rho": 0.15591593366116285,
            "selection_rho": 0.15591593366116285,
            "probe_gain": 0.0035288534418214113,
            "probe_sign": -1.0,
            "alpha": 2.2005128058600687,
            "target_abs_delta_attr": 0.005795128410682082,
            "target_reached_on_calib": true,
            "calib_max_abs_delta_attr": 0.018321878276765347,
            "mean_delta_attr": 0.004314312205679016,
            "mean_abs_delta_attr": 0.009184921324049355,
            "mean_id_cos": 0.9341881861910224,
            "mean_lpips_proxy": 0.04608789988560602,
            "mean_lpips_true": 0.15847351064439863
          },
          {
            "candidate_index": 4,
            "source_group": "sefa",
            "source_rank": 4,
            "rho": 0.20820385217666626,
            "selection_rho": 0.20820385217666626,
            "probe_gain": 0.0005104067531647161,
            "probe_sign": -1.0,
            "alpha": -6.0,
            "target_abs_delta_attr": 0.005795128410682082,
            "target_reached_on_calib": false,
            "calib_max_abs_delta_attr": 0.00559487339342013,
            "mean_delta_attr": -0.001223291917995084,
            "mean_abs_delta_attr": 0.012405109409883153,
            "mean_id_cos": 0.8584109023213387,
            "mean_lpips_proxy": 0.0938028185046278,
            "mean_lpips_true": 0.2916589956730604
          },
          {
            "candidate_index": 5,
            "source_group": "sefa",
            "source_rank": 5,
            "rho": 0.18020420148968697,
            "selection_rho": 0.18020420148968697,
            "probe_gain": 0.00415652513038367,
            "probe_sign": -1.0,
            "alpha": 1.9212790644141489,
            "target_abs_delta_attr": 0.005795128410682082,
            "target_reached_on_calib": true,
            "calib_max_abs_delta_attr": 0.02206372789805755,
            "mean_delta_attr": 0.007955797394970432,
            "mean_abs_delta_attr": 0.01000642983126454,
            "mean_id_cos": 0.9594172975048423,
            "mean_lpips_proxy": 0.022559823148185387,
            "mean_lpips_true": 0.09313260635826737
          }
        ],
        "high_risk": [
          {
            "candidate_index": 2,
            "source_group": "sefa",
            "source_rank": 2,
            "rho": 0.21228170581161976,
            "selection_rho": 0.21228170581161976,
            "probe_gain": 0.0018237010517623276,
            "probe_sign": 1.0,
            "alpha": -5.785369080195326,
            "target_abs_delta_attr": 0.005795128410682082,
            "target_reached_on_calib": true,
            "calib_max_abs_delta_attr": 0.006395893462467939,
            "mean_delta_attr": 0.0013430054968921468,
            "mean_abs_delta_attr": 0.015402238510432653,
            "mean_id_cos": 0.8476290190592408,
            "mean_lpips_proxy": 0.13359730719821528,
            "mean_lpips_true": 0.344283496029675
          },
          {
            "candidate_index": 4,
            "source_group": "sefa",
            "source_rank": 4,
            "rho": 0.20820385217666626,
            "selection_rho": 0.20820385217666626,
            "probe_gain": 0.0005104067531647161,
            "probe_sign": -1.0,
            "alpha": -6.0,
            "target_abs_delta_attr": 0.005795128410682082,
            "target_reached_on_calib": false,
            "calib_max_abs_delta_attr": 0.00559487339342013,
            "mean_delta_attr": -0.001223291917995084,
            "mean_abs_delta_attr": 0.012405109409883153,
            "mean_id_cos": 0.8584109023213387,
            "mean_lpips_proxy": 0.0938028185046278,
            "mean_lpips_true": 0.2916589956730604
          },
          {
            "candidate_index": 0,
            "source_group": "sefa",
            "source_rank": 0,
            "rho": 0.19827763363718987,
            "selection_rho": 0.19827763363718987,
            "probe_gain": 0.0010554329783190042,
            "probe_sign": 1.0,
            "alpha": -6.0,
            "target_abs_delta_attr": 0.005795128410682082,
            "target_reached_on_calib": false,
            "calib_max_abs_delta_attr": 0.004002573259640485,
            "mean_delta_attr": 0.0002476425579516217,
            "mean_abs_delta_attr": 0.010961703010252677,
            "mean_id_cos": 0.9230021014809608,
            "mean_lpips_proxy": 0.054003476863726974,
            "mean_lpips_true": 0.17663446080405265
          },
          {
            "candidate_index": 5,
            "source_group": "sefa",
            "source_rank": 5,
            "rho": 0.18020420148968697,
            "selection_rho": 0.18020420148968697,
            "probe_gain": 0.00415652513038367,
            "probe_sign": -1.0,
            "alpha": 1.9212790644141489,
            "target_abs_delta_attr": 0.005795128410682082,
            "target_reached_on_calib": true,
            "calib_max_abs_delta_attr": 0.02206372789805755,
            "mean_delta_attr": 0.007955797394970432,
            "mean_abs_delta_attr": 0.01000642983126454,
            "mean_id_cos": 0.9594172975048423,
            "mean_lpips_proxy": 0.022559823148185387,
            "mean_lpips_true": 0.09313260635826737
          }
        ]
      },
      "summary": {
        "risk_aware": {
          "n": 4,
          "mean_probe_gain": 0.003100417794485111,
          "mean_rho": 0.18109733681194484,
          "mean_selection_rho": 0.18109733681194484,
          "target_hit_rate_calib": 1.0,
          "mean_abs_delta_attr": 0.011543021309080359,
          "mean_id_cos": 0.9121333542279899,
          "mean_lpips_proxy": 0.06560120946232928,
          "mean_abs_alpha": 3.6840252900849446,
          "mean_lpips_true": 0.20154230756452307
        },
        "gain_only": {
          "n": 4,
          "mean_probe_gain": 0.003100417794485111,
          "mean_rho": 0.18109733681194484,
          "mean_selection_rho": 0.18109733681194484,
          "target_hit_rate_calib": 1.0,
          "mean_abs_delta_attr": 0.011543021309080359,
          "mean_id_cos": 0.9121333542279899,
          "mean_lpips_proxy": 0.06560120946232928,
          "mean_abs_alpha": 3.6840252900849446,
          "mean_lpips_true": 0.20154230756452307
        },
        "low_risk": {
          "n": 4,
          "mean_probe_gain": 0.00290835077612428,
          "mean_rho": 0.17759631876833737,
          "mean_selection_rho": 0.17759631876833737,
          "target_hit_rate_calib": 0.75,
          "mean_abs_delta_attr": 0.010432887434035365,
          "mean_id_cos": 0.9309766248334199,
          "mean_lpips_proxy": 0.045702751878707204,
          "mean_abs_alpha": 3.7376830200361133,
          "mean_lpips_true": 0.15963004875811748
        },
        "random": {
          "n": 4,
          "mean_probe_gain": 0.002772094219835708,
          "mean_rho": 0.18007787340320647,
          "mean_selection_rho": 0.18007787340320647,
          "target_hit_rate_calib": 0.75,
          "mean_abs_delta_attr": 0.010793739033942984,
          "mean_id_cos": 0.9148288250435144,
          "mean_lpips_proxy": 0.05565258728893241,
          "mean_abs_alpha": 3.7376830200361133,
          "mean_lpips_true": 0.18838618247536942
        },
        "high_risk": {
          "n": 4,
          "mean_probe_gain": 0.0018865164784074295,
          "mean_rho": 0.1997418482787907,
          "mean_selection_rho": 0.1997418482787907,
          "target_hit_rate_calib": 0.5,
          "mean_abs_delta_attr": 0.012193870190458256,
          "mean_id_cos": 0.8971148300915956,
          "mean_lpips_proxy": 0.07599085642868886,
          "mean_abs_alpha": 4.9266620361523685,
          "mean_lpips_true": 0.22642738971626386
        }
      }
    },
    "sunny": {
      "candidate_universe": [
        {
          "index": 0,
          "source_group": "sefa",
          "source_rank": 0,
          "rho": 0.19827763363718987,
          "probe_gain": 0.00036962568992748857,
          "probe_sign": -1.0,
          "selection_rho": 0.19827763363718987
        },
        {
          "index": 1,
          "source_group": "sefa",
          "source_rank": 1,
          "rho": 0.1759875062853098,
          "probe_gain": 0.00196302670519799,
          "probe_sign": -1.0,
          "selection_rho": 0.1759875062853098
        },
        {
          "index": 2,
          "source_group": "sefa",
          "source_rank": 2,
          "rho": 0.21228170581161976,
          "probe_gain": 0.0014386730617843568,
          "probe_sign": -1.0,
          "selection_rho": 0.21228170581161976
        },
        {
          "index": 3,
          "source_group": "sefa",
          "source_rank": 3,
          "rho": 0.15591593366116285,
          "probe_gain": 0.005366857869375963,
          "probe_sign": 1.0,
          "selection_rho": 0.15591593366116285
        },
        {
          "index": 4,
          "source_group": "sefa",
          "source_rank": 4,
          "rho": 0.20820385217666626,
          "probe_gain": 0.0018446793546900153,
          "probe_sign": 1.0,
          "selection_rho": 0.20820385217666626
        },
        {
          "index": 5,
          "source_group": "sefa",
          "source_rank": 5,
          "rho": 0.18020420148968697,
          "probe_gain": 0.0030357490468304604,
          "probe_sign": -1.0,
          "selection_rho": 0.18020420148968697
        }
      ],
      "selected_candidate_offsets": {
        "risk_aware": [
          3,
          5,
          1,
          4
        ],
        "gain_only": [
          3,
          5,
          1,
          4
        ],
        "low_risk": [
          3,
          1,
          5,
          0
        ],
        "random": [
          3,
          5,
          2,
          0
        ],
        "high_risk": [
          2,
          4,
          0,
          5
        ]
      },
      "target_abs_delta_attr": 0.008796717302175239,
      "rows": {
        "risk_aware": [
          {
            "candidate_index": 3,
            "source_group": "sefa",
            "source_rank": 3,
            "rho": 0.15591593366116285,
            "selection_rho": 0.15591593366116285,
            "probe_gain": 0.005366857869375963,
            "probe_sign": 1.0,
            "alpha": 3.5546989234077,
            "target_abs_delta_attr": 0.008796717302175239,
            "target_reached_on_calib": true,
            "calib_max_abs_delta_attr": 0.016039712179917842,
            "mean_delta_attr": -0.006503443619294558,
            "mean_abs_delta_attr": 0.011791768723924179,
            "mean_id_cos": 0.9020350389182568,
            "mean_lpips_proxy": 0.07580249482998624,
            "mean_lpips_true": 0.24162434181198478
          },
          {
            "candidate_index": 5,
            "source_group": "sefa",
            "source_rank": 5,
            "rho": 0.18020420148968697,
            "selection_rho": 0.18020420148968697,
            "probe_gain": 0.0030357490468304604,
            "probe_sign": -1.0,
            "alpha": 1.8484674892717359,
            "target_abs_delta_attr": 0.008796717302175239,
            "target_reached_on_calib": true,
            "calib_max_abs_delta_attr": 0.025186266662785783,
            "mean_delta_attr": -0.008615453247330151,
            "mean_abs_delta_attr": 0.010444116880535148,
            "mean_id_cos": 0.9612670782953501,
            "mean_lpips_proxy": 0.021324378743884154,
            "mean_lpips_true": 0.08926198858534917
          },
          {
            "candidate_index": 1,
            "source_group": "sefa",
            "source_rank": 1,
            "rho": 0.1759875062853098,
            "selection_rho": 0.1759875062853098,
            "probe_gain": 0.00196302670519799,
            "probe_sign": -1.0,
            "alpha": 6.0,
            "target_abs_delta_attr": 0.008796717302175239,
            "target_reached_on_calib": false,
            "calib_max_abs_delta_attr": 0.008679339225636795,
            "mean_delta_attr": 0.004806489232578315,
            "mean_abs_delta_attr": 0.015029861402581446,
            "mean_id_cos": 0.8639598172158003,
            "mean_lpips_proxy": 0.09727293346077204,
            "mean_lpips_true": 0.2636647045146674
          },
          {
            "candidate_index": 4,
            "source_group": "sefa",
            "source_rank": 4,
            "rho": 0.20820385217666626,
            "selection_rho": 0.20820385217666626,
            "probe_gain": 0.0018446793546900153,
            "probe_sign": 1.0,
            "alpha": -6.0,
            "target_abs_delta_attr": 0.008796717302175239,
            "target_reached_on_calib": false,
            "calib_max_abs_delta_attr": 0.006926162575837225,
            "mean_delta_attr": -0.0014888382793287747,
            "mean_abs_delta_attr": 0.017116867275035474,
            "mean_id_cos": 0.8584109023213387,
            "mean_lpips_proxy": 0.0938028185046278,
            "mean_lpips_true": 0.2916589956730604
          }
        ],
        "gain_only": [
          {
            "candidate_index": 3,
            "source_group": "sefa",
            "source_rank": 3,
            "rho": 0.15591593366116285,
            "selection_rho": 0.15591593366116285,
            "probe_gain": 0.005366857869375963,
            "probe_sign": 1.0,
            "alpha": 3.5546989234077,
            "target_abs_delta_attr": 0.008796717302175239,
            "target_reached_on_calib": true,
            "calib_max_abs_delta_attr": 0.016039712179917842,
            "mean_delta_attr": -0.006503443619294558,
            "mean_abs_delta_attr": 0.011791768723924179,
            "mean_id_cos": 0.9020350389182568,
            "mean_lpips_proxy": 0.07580249482998624,
            "mean_lpips_true": 0.24162434181198478
          },
          {
            "candidate_index": 5,
            "source_group": "sefa",
            "source_rank": 5,
            "rho": 0.18020420148968697,
            "selection_rho": 0.18020420148968697,
            "probe_gain": 0.0030357490468304604,
            "probe_sign": -1.0,
            "alpha": 1.8484674892717359,
            "target_abs_delta_attr": 0.008796717302175239,
            "target_reached_on_calib": true,
            "calib_max_abs_delta_attr": 0.025186266662785783,
            "mean_delta_attr": -0.008615453247330151,
            "mean_abs_delta_attr": 0.010444116880535148,
            "mean_id_cos": 0.9612670782953501,
            "mean_lpips_proxy": 0.021324378743884154,
            "mean_lpips_true": 0.08926198858534917
          },
          {
            "candidate_index": 1,
            "source_group": "sefa",
            "source_rank": 1,
            "rho": 0.1759875062853098,
            "selection_rho": 0.1759875062853098,
            "probe_gain": 0.00196302670519799,
            "probe_sign": -1.0,
            "alpha": 6.0,
            "target_abs_delta_attr": 0.008796717302175239,
            "target_reached_on_calib": false,
            "calib_max_abs_delta_attr": 0.008679339225636795,
            "mean_delta_attr": 0.004806489232578315,
            "mean_abs_delta_attr": 0.015029861402581446,
            "mean_id_cos": 0.8639598172158003,
            "mean_lpips_proxy": 0.09727293346077204,
            "mean_lpips_true": 0.2636647045146674
          },
          {
            "candidate_index": 4,
            "source_group": "sefa",
            "source_rank": 4,
            "rho": 0.20820385217666626,
            "selection_rho": 0.20820385217666626,
            "probe_gain": 0.0018446793546900153,
            "probe_sign": 1.0,
            "alpha": -6.0,
            "target_abs_delta_attr": 0.008796717302175239,
            "target_reached_on_calib": false,
            "calib_max_abs_delta_attr": 0.006926162575837225,
            "mean_delta_attr": -0.0014888382793287747,
            "mean_abs_delta_attr": 0.017116867275035474,
            "mean_id_cos": 0.8584109023213387,
            "mean_lpips_proxy": 0.0938028185046278,
            "mean_lpips_true": 0.2916589956730604
          }
        ],
        "low_risk": [
          {
            "candidate_index": 3,
            "source_group": "sefa",
            "source_rank": 3,
            "rho": 0.15591593366116285,
            "selection_rho": 0.15591593366116285,
            "probe_gain": 0.005366857869375963,
            "probe_sign": 1.0,
            "alpha": 3.5546989234077,
            "target_abs_delta_attr": 0.008796717302175239,
            "target_reached_on_calib": true,
            "calib_max_abs_delta_attr": 0.016039712179917842,
            "mean_delta_attr": -0.006503443619294558,
            "mean_abs_delta_attr": 0.011791768723924179,
            "mean_id_cos": 0.9020350389182568,
            "mean_lpips_proxy": 0.07580249482998624,
            "mean_lpips_true": 0.24162434181198478
          },
          {
            "candidate_index": 1,
            "source_group": "sefa",
            "source_rank": 1,
            "rho": 0.1759875062853098,
            "selection_rho": 0.1759875062853098,
            "probe_gain": 0.00196302670519799,
            "probe_sign": -1.0,
            "alpha": 6.0,
            "target_abs_delta_attr": 0.008796717302175239,
            "target_reached_on_calib": false,
            "calib_max_abs_delta_attr": 0.008679339225636795,
            "mean_delta_attr": 0.004806489232578315,
            "mean_abs_delta_attr": 0.015029861402581446,
            "mean_id_cos": 0.8639598172158003,
            "mean_lpips_proxy": 0.09727293346077204,
            "mean_lpips_true": 0.2636647045146674
          },
          {
            "candidate_index": 5,
            "source_group": "sefa",
            "source_rank": 5,
            "rho": 0.18020420148968697,
            "selection_rho": 0.18020420148968697,
            "probe_gain": 0.0030357490468304604,
            "probe_sign": -1.0,
            "alpha": 1.8484674892717359,
            "target_abs_delta_attr": 0.008796717302175239,
            "target_reached_on_calib": true,
            "calib_max_abs_delta_attr": 0.025186266662785783,
            "mean_delta_attr": -0.008615453247330151,
            "mean_abs_delta_attr": 0.010444116880535148,
            "mean_id_cos": 0.9612670782953501,
            "mean_lpips_proxy": 0.021324378743884154,
            "mean_lpips_true": 0.08926198858534917
          },
          {
            "candidate_index": 0,
            "source_group": "sefa",
            "source_rank": 0,
            "rho": 0.19827763363718987,
            "selection_rho": 0.19827763363718987,
            "probe_gain": 0.00036962568992748857,
            "probe_sign": -1.0,
            "alpha": 5.887808669684059,
            "target_abs_delta_attr": 0.008796717302175239,
            "target_reached_on_calib": true,
            "calib_max_abs_delta_attr": 0.009186389244860038,
            "mean_delta_attr": -0.001011712709441781,
            "mean_abs_delta_attr": 0.012784450082108378,
            "mean_id_cos": 0.8797005908563733,
            "mean_lpips_proxy": 0.07657633870257996,
            "mean_lpips_true": 0.2524500647559762
          }
        ],
        "random": [
          {
            "candidate_index": 3,
            "source_group": "sefa",
            "source_rank": 3,
            "rho": 0.15591593366116285,
            "selection_rho": 0.15591593366116285,
            "probe_gain": 0.005366857869375963,
            "probe_sign": 1.0,
            "alpha": 3.5546989234077,
            "target_abs_delta_attr": 0.008796717302175239,
            "target_reached_on_calib": true,
            "calib_max_abs_delta_attr": 0.016039712179917842,
            "mean_delta_attr": -0.006503443619294558,
            "mean_abs_delta_attr": 0.011791768723924179,
            "mean_id_cos": 0.9020350389182568,
            "mean_lpips_proxy": 0.07580249482998624,
            "mean_lpips_true": 0.24162434181198478
          },
          {
            "candidate_index": 5,
            "source_group": "sefa",
            "source_rank": 5,
            "rho": 0.18020420148968697,
            "selection_rho": 0.18020420148968697,
            "probe_gain": 0.0030357490468304604,
            "probe_sign": -1.0,
            "alpha": 1.8484674892717359,
            "target_abs_delta_attr": 0.008796717302175239,
            "target_reached_on_calib": true,
            "calib_max_abs_delta_attr": 0.025186266662785783,
            "mean_delta_attr": -0.008615453247330151,
            "mean_abs_delta_attr": 0.010444116880535148,
            "mean_id_cos": 0.9612670782953501,
            "mean_lpips_proxy": 0.021324378743884154,
            "mean_lpips_true": 0.08926198858534917
          },
          {
            "candidate_index": 2,
            "source_group": "sefa",
            "source_rank": 2,
            "rho": 0.21228170581161976,
            "selection_rho": 0.21228170581161976,
            "probe_gain": 0.0014386730617843568,
            "probe_sign": -1.0,
            "alpha": -5.923053730122051,
            "target_abs_delta_attr": 0.008796717302175239,
            "target_reached_on_calib": true,
            "calib_max_abs_delta_attr": 0.00914885153179057,
            "mean_delta_attr": 0.0001851763008744456,
            "mean_abs_delta_attr": 0.01500750640843762,
            "mean_id_cos": 0.8437554892152548,
            "mean_lpips_proxy": 0.13654229044914246,
            "mean_lpips_true": 0.3496655460912734
          },
          {
            "candidate_index": 0,
            "source_group": "sefa",
            "source_rank": 0,
            "rho": 0.19827763363718987,
            "selection_rho": 0.19827763363718987,
            "probe_gain": 0.00036962568992748857,
            "probe_sign": -1.0,
            "alpha": 5.887808669684059,
            "target_abs_delta_attr": 0.008796717302175239,
            "target_reached_on_calib": true,
            "calib_max_abs_delta_attr": 0.009186389244860038,
            "mean_delta_attr": -0.001011712709441781,
            "mean_abs_delta_attr": 0.012784450082108378,
            "mean_id_cos": 0.8797005908563733,
            "mean_lpips_proxy": 0.07657633870257996,
            "mean_lpips_true": 0.2524500647559762
          }
        ],
        "high_risk": [
          {
            "candidate_index": 2,
            "source_group": "sefa",
            "source_rank": 2,
            "rho": 0.21228170581161976,
            "selection_rho": 0.21228170581161976,
            "probe_gain": 0.0014386730617843568,
            "probe_sign": -1.0,
            "alpha": -5.923053730122051,
            "target_abs_delta_attr": 0.008796717302175239,
            "target_reached_on_calib": true,
            "calib_max_abs_delta_attr": 0.00914885153179057,
            "mean_delta_attr": 0.0001851763008744456,
            "mean_abs_delta_attr": 0.01500750640843762,
            "mean_id_cos": 0.8437554892152548,
            "mean_lpips_proxy": 0.13654229044914246,
            "mean_lpips_true": 0.3496655460912734
          },
          {
            "candidate_index": 4,
            "source_group": "sefa",
            "source_rank": 4,
            "rho": 0.20820385217666626,
            "selection_rho": 0.20820385217666626,
            "probe_gain": 0.0018446793546900153,
            "probe_sign": 1.0,
            "alpha": -6.0,
            "target_abs_delta_attr": 0.008796717302175239,
            "target_reached_on_calib": false,
            "calib_max_abs_delta_attr": 0.006926162575837225,
            "mean_delta_attr": -0.0014888382793287747,
            "mean_abs_delta_attr": 0.017116867275035474,
            "mean_id_cos": 0.8584109023213387,
            "mean_lpips_proxy": 0.0938028185046278,
            "mean_lpips_true": 0.2916589956730604
          },
          {
            "candidate_index": 0,
            "source_group": "sefa",
            "source_rank": 0,
            "rho": 0.19827763363718987,
            "selection_rho": 0.19827763363718987,
            "probe_gain": 0.00036962568992748857,
            "probe_sign": -1.0,
            "alpha": 5.887808669684059,
            "target_abs_delta_attr": 0.008796717302175239,
            "target_reached_on_calib": true,
            "calib_max_abs_delta_attr": 0.009186389244860038,
            "mean_delta_attr": -0.001011712709441781,
            "mean_abs_delta_attr": 0.012784450082108378,
            "mean_id_cos": 0.8797005908563733,
            "mean_lpips_proxy": 0.07657633870257996,
            "mean_lpips_true": 0.2524500647559762
          },
          {
            "candidate_index": 5,
            "source_group": "sefa",
            "source_rank": 5,
            "rho": 0.18020420148968697,
            "selection_rho": 0.18020420148968697,
            "probe_gain": 0.0030357490468304604,
            "probe_sign": -1.0,
            "alpha": 1.8484674892717359,
            "target_abs_delta_attr": 0.008796717302175239,
            "target_reached_on_calib": true,
            "calib_max_abs_delta_attr": 0.025186266662785783,
            "mean_delta_attr": -0.008615453247330151,
            "mean_abs_delta_attr": 0.010444116880535148,
            "mean_id_cos": 0.9612670782953501,
            "mean_lpips_proxy": 0.021324378743884154,
            "mean_lpips_true": 0.08926198858534917
          }
        ]
      },
      "summary": {
        "risk_aware": {
          "n": 4,
          "mean_probe_gain": 0.003052578244023607,
          "mean_rho": 0.18007787340320647,
          "mean_selection_rho": 0.18007787340320647,
          "target_hit_rate_calib": 0.5,
          "mean_abs_delta_attr": 0.013595653570519062,
          "mean_id_cos": 0.8964182091876864,
          "mean_lpips_proxy": 0.07205065638481756,
          "mean_abs_alpha": 4.350791603169859,
          "mean_lpips_true": 0.22155250764626544
        },
        "gain_only": {
          "n": 4,
          "mean_probe_gain": 0.003052578244023607,
          "mean_rho": 0.18007787340320647,
          "mean_selection_rho": 0.18007787340320647,
          "target_hit_rate_calib": 0.5,
          "mean_abs_delta_attr": 0.013595653570519062,
          "mean_id_cos": 0.8964182091876864,
          "mean_lpips_proxy": 0.07205065638481756,
          "mean_abs_alpha": 4.350791603169859,
          "mean_lpips_true": 0.22155250764626544
        },
        "low_risk": {
          "n": 4,
          "mean_probe_gain": 0.0026838148278329754,
          "mean_rho": 0.17759631876833737,
          "mean_selection_rho": 0.17759631876833737,
          "target_hit_rate_calib": 0.75,
          "mean_abs_delta_attr": 0.012512549272287288,
          "mean_id_cos": 0.9017406313214451,
          "mean_lpips_proxy": 0.0677440364343056,
          "mean_abs_alpha": 4.322743770590874,
          "mean_lpips_true": 0.21175027491699439
        },
        "random": {
          "n": 4,
          "mean_probe_gain": 0.002552726416979567,
          "mean_rho": 0.18666986864991486,
          "mean_selection_rho": 0.18666986864991486,
          "target_hit_rate_calib": 1.0,
          "mean_abs_delta_attr": 0.012506960523751331,
          "mean_id_cos": 0.8966895493213087,
          "mean_lpips_proxy": 0.0775613756813982,
          "mean_abs_alpha": 4.303507203121386,
          "mean_lpips_true": 0.2332504853111459
        },
        "high_risk": {
          "n": 4,
          "mean_probe_gain": 0.0016721817883080803,
          "mean_rho": 0.1997418482787907,
          "mean_selection_rho": 0.1997418482787907,
          "target_hit_rate_calib": 0.75,
          "mean_abs_delta_attr": 0.013838235161529155,
          "mean_id_cos": 0.8857835151720792,
          "mean_lpips_proxy": 0.08206145660005859,
          "mean_abs_alpha": 4.914832472269462,
          "mean_lpips_true": 0.2457591487764148
        }
      }
    },
    "vegetation": {
      "candidate_universe": [
        {
          "index": 0,
          "source_group": "sefa",
          "source_rank": 0,
          "rho": 0.15870503894984722,
          "probe_gain": 0.0018885079771280289,
          "probe_sign": 1.0,
          "selection_rho": 0.15870503894984722
        },
        {
          "index": 1,
          "source_group": "sefa",
          "source_rank": 1,
          "rho": 0.1209812993183732,
          "probe_gain": 0.0015044592437334359,
          "probe_sign": 1.0,
          "selection_rho": 0.1209812993183732
        },
        {
          "index": 2,
          "source_group": "sefa",
          "source_rank": 2,
          "rho": 0.042173726949840784,
          "probe_gain": 0.0015231544384732842,
          "probe_sign": 1.0,
          "selection_rho": 0.042173726949840784
        },
        {
          "index": 3,
          "source_group": "sefa",
          "source_rank": 3,
          "rho": 0.06474714307114482,
          "probe_gain": 0.0012278309441171587,
          "probe_sign": -1.0,
          "selection_rho": 0.06474714307114482
        },
        {
          "index": 4,
          "source_group": "sefa",
          "source_rank": 4,
          "rho": 0.06888374453410506,
          "probe_gain": 0.0010149451263714582,
          "probe_sign": -1.0,
          "selection_rho": 0.06888374453410506
        },
        {
          "index": 5,
          "source_group": "sefa",
          "source_rank": 5,
          "rho": 0.12305817287415266,
          "probe_gain": 0.0011242285836488008,
          "probe_sign": -1.0,
          "selection_rho": 0.12305817287415266
        }
      ],
      "selected_candidate_offsets": {
        "risk_aware": [
          2,
          3,
          1,
          0
        ],
        "gain_only": [
          0,
          2,
          1,
          3
        ],
        "low_risk": [
          2,
          3,
          4,
          1
        ],
        "random": [
          4,
          1,
          3,
          2
        ],
        "high_risk": [
          0,
          5,
          1,
          4
        ]
      },
      "target_abs_delta_attr": 0.00241609003933263,
      "rows": {
        "risk_aware": [
          {
            "candidate_index": 2,
            "source_group": "sefa",
            "source_rank": 2,
            "rho": 0.042173726949840784,
            "selection_rho": 0.042173726949840784,
            "probe_gain": 0.0015231544384732842,
            "probe_sign": 1.0,
            "alpha": 6.0,
            "target_abs_delta_attr": 0.00241609003933263,
            "target_reached_on_calib": false,
            "calib_max_abs_delta_attr": 0.0013838885352015495,
            "mean_delta_attr": 0.005816861565108411,
            "mean_abs_delta_attr": 0.012588558791321702,
            "mean_id_cos": 0.942858126014471,
            "mean_lpips_proxy": 0.021701301404391415,
            "mean_lpips_true": 0.10435923794284463
          },
          {
            "candidate_index": 3,
            "source_group": "sefa",
            "source_rank": 3,
            "rho": 0.06474714307114482,
            "selection_rho": 0.06474714307114482,
            "probe_gain": 0.0012278309441171587,
            "probe_sign": -1.0,
            "alpha": 2.3330173429042564,
            "target_abs_delta_attr": 0.00241609003933263,
            "target_reached_on_calib": true,
            "calib_max_abs_delta_attr": 0.005784103064797819,
            "mean_delta_attr": -0.0014054274579393677,
            "mean_abs_delta_attr": 0.005322823744791094,
            "mean_id_cos": 0.9889880605041981,
            "mean_lpips_proxy": 0.004683037612267071,
            "mean_lpips_true": 0.02444154351542238
          },
          {
            "candidate_index": 1,
            "source_group": "sefa",
            "source_rank": 1,
            "rho": 0.1209812993183732,
            "selection_rho": 0.1209812993183732,
            "probe_gain": 0.0015044592437334359,
            "probe_sign": 1.0,
            "alpha": -4.4044601602966855,
            "target_abs_delta_attr": 0.00241609003933263,
            "target_reached_on_calib": true,
            "calib_max_abs_delta_attr": 0.00418867968255654,
            "mean_delta_attr": 0.0034099132790288422,
            "mean_abs_delta_attr": 0.010133851090358803,
            "mean_id_cos": 0.920498738065362,
            "mean_lpips_proxy": 0.02019653483876027,
            "mean_lpips_true": 0.14605460315942764
          },
          {
            "candidate_index": 0,
            "source_group": "sefa",
            "source_rank": 0,
            "rho": 0.15870503894984722,
            "selection_rho": 0.15870503894984722,
            "probe_gain": 0.0018885079771280289,
            "probe_sign": 1.0,
            "alpha": -3.7595906389109732,
            "target_abs_delta_attr": 0.00241609003933263,
            "target_reached_on_calib": true,
            "calib_max_abs_delta_attr": 0.0037990930723026395,
            "mean_delta_attr": -0.0010651826160028577,
            "mean_abs_delta_attr": 0.006457594892708585,
            "mean_id_cos": 0.9772233879193664,
            "mean_lpips_proxy": 0.00675765343112289,
            "mean_lpips_true": 0.043023916106903926
          }
        ],
        "gain_only": [
          {
            "candidate_index": 0,
            "source_group": "sefa",
            "source_rank": 0,
            "rho": 0.15870503894984722,
            "selection_rho": 0.15870503894984722,
            "probe_gain": 0.0018885079771280289,
            "probe_sign": 1.0,
            "alpha": -3.7595906389109732,
            "target_abs_delta_attr": 0.00241609003933263,
            "target_reached_on_calib": true,
            "calib_max_abs_delta_attr": 0.0037990930723026395,
            "mean_delta_attr": -0.0010651826160028577,
            "mean_abs_delta_attr": 0.006457594892708585,
            "mean_id_cos": 0.9772233879193664,
            "mean_lpips_proxy": 0.00675765343112289,
            "mean_lpips_true": 0.043023916106903926
          },
          {
            "candidate_index": 2,
            "source_group": "sefa",
            "source_rank": 2,
            "rho": 0.042173726949840784,
            "selection_rho": 0.042173726949840784,
            "probe_gain": 0.0015231544384732842,
            "probe_sign": 1.0,
            "alpha": 6.0,
            "target_abs_delta_attr": 0.00241609003933263,
            "target_reached_on_calib": false,
            "calib_max_abs_delta_attr": 0.0013838885352015495,
            "mean_delta_attr": 0.005816861565108411,
            "mean_abs_delta_attr": 0.012588558791321702,
            "mean_id_cos": 0.942858126014471,
            "mean_lpips_proxy": 0.021701301404391415,
            "mean_lpips_true": 0.10435923794284463
          },
          {
            "candidate_index": 1,
            "source_group": "sefa",
            "source_rank": 1,
            "rho": 0.1209812993183732,
            "selection_rho": 0.1209812993183732,
            "probe_gain": 0.0015044592437334359,
            "probe_sign": 1.0,
            "alpha": -4.4044601602966855,
            "target_abs_delta_attr": 0.00241609003933263,
            "target_reached_on_calib": true,
            "calib_max_abs_delta_attr": 0.00418867968255654,
            "mean_delta_attr": 0.0034099132790288422,
            "mean_abs_delta_attr": 0.010133851090358803,
            "mean_id_cos": 0.920498738065362,
            "mean_lpips_proxy": 0.02019653483876027,
            "mean_lpips_true": 0.14605460315942764
          },
          {
            "candidate_index": 3,
            "source_group": "sefa",
            "source_rank": 3,
            "rho": 0.06474714307114482,
            "selection_rho": 0.06474714307114482,
            "probe_gain": 0.0012278309441171587,
            "probe_sign": -1.0,
            "alpha": 2.3330173429042564,
            "target_abs_delta_attr": 0.00241609003933263,
            "target_reached_on_calib": true,
            "calib_max_abs_delta_attr": 0.005784103064797819,
            "mean_delta_attr": -0.0014054274579393677,
            "mean_abs_delta_attr": 0.005322823744791094,
            "mean_id_cos": 0.9889880605041981,
            "mean_lpips_proxy": 0.004683037612267071,
            "mean_lpips_true": 0.02444154351542238
          }
        ],
        "low_risk": [
          {
            "candidate_index": 2,
            "source_group": "sefa",
            "source_rank": 2,
            "rho": 0.042173726949840784,
            "selection_rho": 0.042173726949840784,
            "probe_gain": 0.0015231544384732842,
            "probe_sign": 1.0,
            "alpha": 6.0,
            "target_abs_delta_attr": 0.00241609003933263,
            "target_reached_on_calib": false,
            "calib_max_abs_delta_attr": 0.0013838885352015495,
            "mean_delta_attr": 0.005816861565108411,
            "mean_abs_delta_attr": 0.012588558791321702,
            "mean_id_cos": 0.942858126014471,
            "mean_lpips_proxy": 0.021701301404391415,
            "mean_lpips_true": 0.10435923794284463
          },
          {
            "candidate_index": 3,
            "source_group": "sefa",
            "source_rank": 3,
            "rho": 0.06474714307114482,
            "selection_rho": 0.06474714307114482,
            "probe_gain": 0.0012278309441171587,
            "probe_sign": -1.0,
            "alpha": 2.3330173429042564,
            "target_abs_delta_attr": 0.00241609003933263,
            "target_reached_on_calib": true,
            "calib_max_abs_delta_attr": 0.005784103064797819,
            "mean_delta_attr": -0.0014054274579393677,
            "mean_abs_delta_attr": 0.005322823744791094,
            "mean_id_cos": 0.9889880605041981,
            "mean_lpips_proxy": 0.004683037612267071,
            "mean_lpips_true": 0.02444154351542238
          },
          {
            "candidate_index": 4,
            "source_group": "sefa",
            "source_rank": 4,
            "rho": 0.06888374453410506,
            "selection_rho": 0.06888374453410506,
            "probe_gain": 0.0010149451263714582,
            "probe_sign": -1.0,
            "alpha": 6.0,
            "target_abs_delta_attr": 0.00241609003933263,
            "target_reached_on_calib": false,
            "calib_max_abs_delta_attr": 0.001955089028342627,
            "mean_delta_attr": -0.00556676417181734,
            "mean_abs_delta_attr": 0.010779360876767896,
            "mean_id_cos": 0.9332137787714601,
            "mean_lpips_proxy": 0.032635812283842824,
            "mean_lpips_true": 0.1273944589192979
          },
          {
            "candidate_index": 1,
            "source_group": "sefa",
            "source_rank": 1,
            "rho": 0.1209812993183732,
            "selection_rho": 0.1209812993183732,
            "probe_gain": 0.0015044592437334359,
            "probe_sign": 1.0,
            "alpha": -4.4044601602966855,
            "target_abs_delta_attr": 0.00241609003933263,
            "target_reached_on_calib": true,
            "calib_max_abs_delta_attr": 0.00418867968255654,
            "mean_delta_attr": 0.0034099132790288422,
            "mean_abs_delta_attr": 0.010133851090358803,
            "mean_id_cos": 0.920498738065362,
            "mean_lpips_proxy": 0.02019653483876027,
            "mean_lpips_true": 0.14605460315942764
          }
        ],
        "random": [
          {
            "candidate_index": 4,
            "source_group": "sefa",
            "source_rank": 4,
            "rho": 0.06888374453410506,
            "selection_rho": 0.06888374453410506,
            "probe_gain": 0.0010149451263714582,
            "probe_sign": -1.0,
            "alpha": 6.0,
            "target_abs_delta_attr": 0.00241609003933263,
            "target_reached_on_calib": false,
            "calib_max_abs_delta_attr": 0.001955089028342627,
            "mean_delta_attr": -0.00556676417181734,
            "mean_abs_delta_attr": 0.010779360876767896,
            "mean_id_cos": 0.9332137787714601,
            "mean_lpips_proxy": 0.032635812283842824,
            "mean_lpips_true": 0.1273944589192979
          },
          {
            "candidate_index": 1,
            "source_group": "sefa",
            "source_rank": 1,
            "rho": 0.1209812993183732,
            "selection_rho": 0.1209812993183732,
            "probe_gain": 0.0015044592437334359,
            "probe_sign": 1.0,
            "alpha": -4.4044601602966855,
            "target_abs_delta_attr": 0.00241609003933263,
            "target_reached_on_calib": true,
            "calib_max_abs_delta_attr": 0.00418867968255654,
            "mean_delta_attr": 0.0034099132790288422,
            "mean_abs_delta_attr": 0.010133851090358803,
            "mean_id_cos": 0.920498738065362,
            "mean_lpips_proxy": 0.02019653483876027,
            "mean_lpips_true": 0.14605460315942764
          },
          {
            "candidate_index": 3,
            "source_group": "sefa",
            "source_rank": 3,
            "rho": 0.06474714307114482,
            "selection_rho": 0.06474714307114482,
            "probe_gain": 0.0012278309441171587,
            "probe_sign": -1.0,
            "alpha": 2.3330173429042564,
            "target_abs_delta_attr": 0.00241609003933263,
            "target_reached_on_calib": true,
            "calib_max_abs_delta_attr": 0.005784103064797819,
            "mean_delta_attr": -0.0014054274579393677,
            "mean_abs_delta_attr": 0.005322823744791094,
            "mean_id_cos": 0.9889880605041981,
            "mean_lpips_proxy": 0.004683037612267071,
            "mean_lpips_true": 0.02444154351542238
          },
          {
            "candidate_index": 2,
            "source_group": "sefa",
            "source_rank": 2,
            "rho": 0.042173726949840784,
            "selection_rho": 0.042173726949840784,
            "probe_gain": 0.0015231544384732842,
            "probe_sign": 1.0,
            "alpha": 6.0,
            "target_abs_delta_attr": 0.00241609003933263,
            "target_reached_on_calib": false,
            "calib_max_abs_delta_attr": 0.0013838885352015495,
            "mean_delta_attr": 0.005816861565108411,
            "mean_abs_delta_attr": 0.012588558791321702,
            "mean_id_cos": 0.942858126014471,
            "mean_lpips_proxy": 0.021701301404391415,
            "mean_lpips_true": 0.10435923794284463
          }
        ],
        "high_risk": [
          {
            "candidate_index": 0,
            "source_group": "sefa",
            "source_rank": 0,
            "rho": 0.15870503894984722,
            "selection_rho": 0.15870503894984722,
            "probe_gain": 0.0018885079771280289,
            "probe_sign": 1.0,
            "alpha": -3.7595906389109732,
            "target_abs_delta_attr": 0.00241609003933263,
            "target_reached_on_calib": true,
            "calib_max_abs_delta_attr": 0.0037990930723026395,
            "mean_delta_attr": -0.0010651826160028577,
            "mean_abs_delta_attr": 0.006457594892708585,
            "mean_id_cos": 0.9772233879193664,
            "mean_lpips_proxy": 0.00675765343112289,
            "mean_lpips_true": 0.043023916106903926
          },
          {
            "candidate_index": 5,
            "source_group": "sefa",
            "source_rank": 5,
            "rho": 0.12305817287415266,
            "selection_rho": 0.12305817287415266,
            "probe_gain": 0.0011242285836488008,
            "probe_sign": -1.0,
            "alpha": -3.789760185667813,
            "target_abs_delta_attr": 0.00241609003933263,
            "target_reached_on_calib": true,
            "calib_max_abs_delta_attr": 0.006115988304372877,
            "mean_delta_attr": 0.0017104256767197512,
            "mean_abs_delta_attr": 0.011256095596763771,
            "mean_id_cos": 0.9552112417295575,
            "mean_lpips_proxy": 0.05041255953256041,
            "mean_lpips_true": 0.09940058557549492
          },
          {
            "candidate_index": 1,
            "source_group": "sefa",
            "source_rank": 1,
            "rho": 0.1209812993183732,
            "selection_rho": 0.1209812993183732,
            "probe_gain": 0.0015044592437334359,
            "probe_sign": 1.0,
            "alpha": -4.4044601602966855,
            "target_abs_delta_attr": 0.00241609003933263,
            "target_reached_on_calib": true,
            "calib_max_abs_delta_attr": 0.00418867968255654,
            "mean_delta_attr": 0.0034099132790288422,
            "mean_abs_delta_attr": 0.010133851090358803,
            "mean_id_cos": 0.920498738065362,
            "mean_lpips_proxy": 0.02019653483876027,
            "mean_lpips_true": 0.14605460315942764
          },
          {
            "candidate_index": 4,
            "source_group": "sefa",
            "source_rank": 4,
            "rho": 0.06888374453410506,
            "selection_rho": 0.06888374453410506,
            "probe_gain": 0.0010149451263714582,
            "probe_sign": -1.0,
            "alpha": 6.0,
            "target_abs_delta_attr": 0.00241609003933263,
            "target_reached_on_calib": false,
            "calib_max_abs_delta_attr": 0.001955089028342627,
            "mean_delta_attr": -0.00556676417181734,
            "mean_abs_delta_attr": 0.010779360876767896,
            "mean_id_cos": 0.9332137787714601,
            "mean_lpips_proxy": 0.032635812283842824,
            "mean_lpips_true": 0.1273944589192979
          }
        ]
      },
      "summary": {
        "risk_aware": {
          "n": 4,
          "mean_probe_gain": 0.001535988150862977,
          "mean_rho": 0.09665180207230151,
          "mean_selection_rho": 0.09665180207230151,
          "target_hit_rate_calib": 0.75,
          "mean_abs_delta_attr": 0.008625707129795046,
          "mean_id_cos": 0.9573920781258494,
          "mean_lpips_proxy": 0.013334631821635412,
          "mean_abs_alpha": 4.1242670355279785,
          "mean_lpips_true": 0.07946982518114964
        },
        "gain_only": {
          "n": 4,
          "mean_probe_gain": 0.001535988150862977,
          "mean_rho": 0.09665180207230151,
          "mean_selection_rho": 0.09665180207230151,
          "target_hit_rate_calib": 0.75,
          "mean_abs_delta_attr": 0.008625707129795046,
          "mean_id_cos": 0.9573920781258494,
          "mean_lpips_proxy": 0.013334631821635412,
          "mean_abs_alpha": 4.1242670355279785,
          "mean_lpips_true": 0.07946982518114964
        },
        "low_risk": {
          "n": 4,
          "mean_probe_gain": 0.0013175974381738342,
          "mean_rho": 0.07419647846836597,
          "mean_selection_rho": 0.07419647846836597,
          "target_hit_rate_calib": 0.5,
          "mean_abs_delta_attr": 0.009706148625809874,
          "mean_id_cos": 0.9463896758388728,
          "mean_lpips_proxy": 0.019804171534815396,
          "mean_abs_alpha": 4.684369375800236,
          "mean_lpips_true": 0.10056246088424814
        },
        "random": {
          "n": 4,
          "mean_probe_gain": 0.0013175974381738342,
          "mean_rho": 0.07419647846836597,
          "mean_selection_rho": 0.07419647846836597,
          "target_hit_rate_calib": 0.5,
          "mean_abs_delta_attr": 0.009706148625809874,
          "mean_id_cos": 0.9463896758388728,
          "mean_lpips_proxy": 0.019804171534815396,
          "mean_abs_alpha": 4.684369375800236,
          "mean_lpips_true": 0.10056246088424814
        },
        "high_risk": {
          "n": 4,
          "mean_probe_gain": 0.001383035232720431,
          "mean_rho": 0.11790706391911954,
          "mean_selection_rho": 0.11790706391911954,
          "target_hit_rate_calib": 0.75,
          "mean_abs_delta_attr": 0.009656725614149764,
          "mean_id_cos": 0.9465367866214365,
          "mean_lpips_proxy": 0.0275006400215716,
          "mean_abs_alpha": 4.488452746218868,
          "mean_lpips_true": 0.1039683909402811
        }
      }
    }
  },
  "config": {
    "domain": "church",
    "attrs": [
      "clouds",
      "sunny",
      "vegetation"
    ],
    "methods": [
      "sefa"
    ],
    "candidate_k": 6,
    "ganspace_samples": 2048,
    "k_select": 4,
    "min_gain_quantile": 0.5,
    "risk_power": 1.0,
    "n_risk": 8,
    "n_probe": 16,
    "probe_alpha": 1.0,
    "n_calib": 16,
    "n_test": 64,
    "alpha_steps": 7,
    "max_alpha": 6.0,
    "target_quantile": 0.25,
    "target_source": "universe",
    "batch": 4,
    "out": "experiments/out/control_church_structured_source_ablation/sefa_only_seed_2028",
    "seed": 2028,
    "true_lpips": true,
    "lpips_net": "alex",
    "lpips_size": 256,
    "risk_selection_mode": "actual",
    "protocol": "/mnt/20t/study/HIGAN/paper/experiments/protocols/control_v29_church_structured_source_ablation.json",
    "protocol_key": "church_structured_source_ablation_sefa_only_seed_2028"
  },
  "_meta": {
    "seed": 2028,
    "deterministic_set": true,
    "timestamp_utc": "2026-05-26T10:42:29.515993+00:00",
    "python": "3.12.9",
    "torch": "2.2.2+cu121",
    "numpy": "1.26.4",
    "cuda": "12.1",
    "cudnn_version": 8902,
    "gpu_name": "NVIDIA GeForce RTX 3070",
    "git_commit": "1051367f5aabbde5a9610cc5c997d7dc6a04ffb2",
    "git_dirty": true,
    "script": "experiments/control/run_cross_domain_risk_aware_controller.py",
    "execution": {
      "argv": [
        "experiments/control/run_cross_domain_risk_aware_controller.py",
        "--domain",
        "church",
        "--attrs",
        "clouds",
        "sunny",
        "vegetation",
        "--methods",
        "sefa",
        "--candidate-k",
        "6",
        "--ganspace-samples",
        "2048",
        "--k-select",
        "4",
        "--min-gain-quantile",
        "0.5",
        "--risk-power",
        "1.0",
        "--risk-selection-mode",
        "actual",
        "--target-source",
        "universe",
        "--true-lpips",
        "--lpips-net",
        "alex",
        "--lpips-size",
        "256",
        "--n-risk",
        "8",
        "--n-probe",
        "16",
        "--probe-alpha",
        "1.0",
        "--n-calib",
        "16",
        "--n-test",
        "64",
        "--alpha-steps",
        "7",
        "--max-alpha",
        "6",
        "--target-quantile",
        "0.25",
        "--batch",
        "4",
        "--out",
        "experiments/out/control_church_structured_source_ablation/sefa_only_seed_2028",
        "--seed",
        "2028",
        "--protocol",
        "/mnt/20t/study/HIGAN/paper/experiments/protocols/control_v29_church_structured_source_ablation.json",
        "--protocol-key",
        "church_structured_source_ablation_sefa_only_seed_2028"
      ],
      "cwd": "/mnt/20t/study/HIGAN/paper",
      "hostname": "server",
      "pid": 1426043,
      "timestamp_utc": "2026-05-26T10:42:29.515557+00:00",
      "protocol_path": "/mnt/20t/study/HIGAN/paper/experiments/protocols/control_v29_church_structured_source_ablation.json",
      "protocol_key": "church_structured_source_ablation_sefa_only_seed_2028",
      "protocol_sha256": "c213e56cc571e849301c643321160300d78f69e97a820365d0d28414878c84e7",
      "protocol_version": "control_v29_church_structured_source_ablation"
    }
  }
}